setup.py
storagex/__init__.py
storagex/commandline.py
storagex/file_meta_info.py
storagex/storage.py
storagex.egg-info/PKG-INFO
storagex.egg-info/SOURCES.txt
storagex.egg-info/dependency_links.txt
storagex.egg-info/entry_points.txt
storagex.egg-info/requires.txt
storagex.egg-info/top_level.txt
storagex/backend/__init__.py
storagex/backend/baidushitu_backend.py
storagex/backend/base_backend.py
storagex/serializer/__init__.py
storagex/serializer/base_serializer.py
storagex/serializer/png_serializer.py