Metadata-Version: 1.0
Name: storagex
Version: 0.3
Summary: just storagex
Home-page: https://github.com/rainx/storagex
Author: RainX<Jing Xu>
Author-email: i@rainx.cc
License: UNKNOWN
Platform: UNKNOWN
